odoo8_addon_l10n_es_subcontractor_certificate-8.0.1.0.0.99.dev18-py3.6-nspkg.pth
odoo_addons/l10n_es_subcontractor_certificate/README.rst
odoo_addons/l10n_es_subcontractor_certificate/__init__.py
odoo_addons/l10n_es_subcontractor_certificate/__openerp__.py
odoo_addons/l10n_es_subcontractor_certificate/i18n/bg.po
odoo_addons/l10n_es_subcontractor_certificate/i18n/ca.po
odoo_addons/l10n_es_subcontractor_certificate/i18n/cs.po
odoo_addons/l10n_es_subcontractor_certificate/i18n/en_US.po
odoo_addons/l10n_es_subcontractor_certificate/i18n/es.po
odoo_addons/l10n_es_subcontractor_certificate/i18n/es_CR.po
odoo_addons/l10n_es_subcontractor_certificate/i18n/eu.po
odoo_addons/l10n_es_subcontractor_certificate/i18n/fr.po
odoo_addons/l10n_es_subcontractor_certificate/i18n/gl.po
odoo_addons/l10n_es_subcontractor_certificate/i18n/hr.po
odoo_addons/l10n_es_subcontractor_certificate/i18n/l10n_es_subcontractor_certificate.pot
odoo_addons/l10n_es_subcontractor_certificate/i18n/nl.po
odoo_addons/l10n_es_subcontractor_certificate/i18n/pl.po
odoo_addons/l10n_es_subcontractor_certificate/i18n/pt.po
odoo_addons/l10n_es_subcontractor_certificate/i18n/pt_BR.po
odoo_addons/l10n_es_subcontractor_certificate/i18n/ru.po
odoo_addons/l10n_es_subcontractor_certificate/i18n/sl.po
odoo_addons/l10n_es_subcontractor_certificate/i18n/sv.po
odoo_addons/l10n_es_subcontractor_certificate/i18n/tr.po
odoo_addons/l10n_es_subcontractor_certificate/i18n/vi.po
odoo_addons/l10n_es_subcontractor_certificate/models/__init__.py
odoo_addons/l10n_es_subcontractor_certificate/models/subcontractor_certificate.py
odoo_addons/l10n_es_subcontractor_certificate/static/description/icon.png
odoo_addons/l10n_es_subcontractor_certificate/views/subcontractor_certificate_view.xml
odoo8_addon_l10n_es_subcontractor_certificate-8.0.1.0.0.99.dev18.dist-info/METADATA
odoo8_addon_l10n_es_subcontractor_certificate-8.0.1.0.0.99.dev18.dist-info/WHEEL
odoo8_addon_l10n_es_subcontractor_certificate-8.0.1.0.0.99.dev18.dist-info/namespace_packages.txt
odoo8_addon_l10n_es_subcontractor_certificate-8.0.1.0.0.99.dev18.dist-info/top_level.txt
odoo8_addon_l10n_es_subcontractor_certificate-8.0.1.0.0.99.dev18.dist-info/RECORD
