Metadata-Version: 2.1
Name: odoo8-addon-l10n-es-subcontractor-certificate
Version: 8.0.1.0.0.99.dev18
Summary: Certificado de subcontratista
Home-page: http://www.domatix.com/
Author: Domatix,Odoo Community Association (OCA)
Author-email: support@odoo-community.org
License: UNKNOWN
Platform: UNKNOWN
Classifier: Programming Language :: Python
Classifier: Framework :: Odoo
Requires-Python: ~=2.7
Requires-Dist: odoo (<9.0a,>=8.0a)
